setup.py
punj_distributions1/Binomialdistribution.py
punj_distributions1/Gaussiandistribution.py
punj_distributions1/Generaldistribution.py
punj_distributions1/__init__.py
punj_distributions1.egg-info/PKG-INFO
punj_distributions1.egg-info/SOURCES.txt
punj_distributions1.egg-info/dependency_links.txt
punj_distributions1.egg-info/not-zip-safe
punj_distributions1.egg-info/top_level.txt